{
  "Ваша фамилия": "",
  "Ваше имя": "",
  "Введите корректные пользовательские данные": "",
  "Введите корректный возраст": "",
  "Введите корректный город": "",
  "Введите корректный логин": "",
  "Возраст": "",
  "Вы пытаетесь отправить пустой профиль": "",
  "Город": "",
  "Логин": "",
  "Отменить": "",
  "Ошибка при обновлении данных": {
    " Попробуйте ещё раз": {
      "": ""
    },
    " Попробуйте ещё разю": ""
  },
  "Попробуйте перезагрузить страницу": "",
  "Произошла ошибка": "",
  "Профиль": "",
  "Профиль не найден": "",
  "Редактировать": "",
  "Сохранить": "",
  "Фото": ""
}
